pytest_mock/__init__.py
pytest_mock/_util.py
pytest_mock/_version.py
pytest_mock/plugin.py
pytest_mock/py.typed
pytest_mock-3.13.0.dist-info/LICENSE
pytest_mock-3.13.0.dist-info/METADATA
pytest_mock-3.13.0.dist-info/WHEEL
pytest_mock-3.13.0.dist-info/entry_points.txt
pytest_mock-3.13.0.dist-info/top_level.txt
pytest_mock-3.13.0.dist-info/RECORD
